dedis_cluster/__init__.py
dedis_cluster/cache.py
dedis_cluster/connection.py
dedis_cluster/exceptions.py
dedis_cluster/utils.py
dedis_cluster/client/__init__.py
dedis_cluster/client/default.py
dedis_cluster/compressors/__init__.py
dedis_cluster/compressors/base.py
dedis_cluster/compressors/identity.py
dedis_cluster/compressors/lz4.py
dedis_cluster/compressors/lzma.py
dedis_cluster/compressors/zlib.py
dedis_cluster/serializers/__init__.py
dedis_cluster/serializers/base.py
dedis_cluster/serializers/json.py
dedis_cluster/serializers/msgpack.py
dedis_cluster/serializers/pickle.py
dedis_cluster-1.0.2.dist-info/LICENSE
dedis_cluster-1.0.2.dist-info/METADATA
dedis_cluster-1.0.2.dist-info/WHEEL
dedis_cluster-1.0.2.dist-info/top_level.txt
dedis_cluster-1.0.2.dist-info/RECORD
